README.md
setup.cfg
setup.py
inspectortiger/__init__.py
inspectortiger/__main__.py
inspectortiger/config.py
inspectortiger/inspector.py
inspectortiger/plugin.py
inspectortiger/reports.py
inspectortiger/session.py
inspectortiger/utils.py
inspectortiger/plugins/__init__.py
inspectortiger/plugins/context.py
inspectortiger/plugins/general.py
inspectortiger/plugins/parentize.py
inspectortiger/plugins/upgrade.py
inspectortiger/plugins/community/__init__.py
inspectortiger/server/__init__.py
inspectortiger/server/__main__.py
inspectortiger/server/handler.py
it.egg-info/PKG-INFO
it.egg-info/SOURCES.txt
it.egg-info/dependency_links.txt
it.egg-info/entry_points.txt
it.egg-info/top_level.txt