Metadata-Version: 2.1
Name: it
Version: 0.9.0
Summary: Modern python code review tool / framework
Home-page: https://github.com/thg-consulting/inspectortiger
Author: thg
License: UNKNOWN
Platform: UNKNOWN
Requires-Python: >=3.7
